
[
 {
 "scene": "Always have multiple pimples on your face",
 "category": "gross",
 "magnitude": "light"
 },
 {
 "scene": "Lick a persons face every time they say a sentence to you",
 "category": "gross",
 "magnitude": "light"
 },
 {
 "scene": "",
 "category": "gross",
 "magnitude": "light"
 },
 {
 "scene": "Feet always stink",
 "category": "gross",
 "magnitude": "light"
 },
 {
 "scene": "Constant bad breath",
 "category": "gross",
 "magnitude": "light"
 },
 {
 "scene": "Constantly sweeting",
 "category": "gross",
 "magnitude": "light"
 },
 {
 "scene": "Lick the dirt of a homless person fingers",
 "category": "gross",
 "magnitude": "stiff"
 },
 {
 "scene": "Pimple filled eye brows",
 "category": "gross",
 "magnitude": "stiff"
 },
 {
 "scene": "have to eat a very moldy meal once a week",
 "category": "gross",
 "magnitude": "stiff"
 },
 {
 "scene": "Have an extra nipple",
 "category": "gross",
 "magnitude": "stiff"
 },
 {
 "scene": "Smell strong pungent vomit smell when ever you get tired",
 "category": "gross",
 "magnitude": "stiff"
 },
 {
 "scene": "Can only shower once a month",
 "category": "gross",
 "magnitude": "heavy"
 },
 {
 "scene": "",
 "category": "gross",
 "magnitude": "heavy"
 },
 {
 "scene": "",
 "category": "gross",
 "magnitude": "heavy"
 },
 {
 "scene": "Lick the seat of every porta potty at Cochella",
 "category": "gross",
 "magnitude": "heavy"
 },
 {
 "scene": "",
 "category": "gross",
 "magnitude": "heavy"
 },
 {
 "scene": "",
 "category": "gross",
 "magnitude": "extreme"
 },
 {
 "scene": "",
 "category": "gross",
 "magnitude": "extreme"
 },
 {
 "scene": "",
 "category": "gross",
 "magnitude": "extreme"
 },
 {
 "scene": "",
 "category": "gross",
 "magnitude": "extreme"
 },
 {
 "scene": "Eat vomit",
 "category": "gross",
 "magnitude": "extreme"
 }
 ]
